adelecv/__init__.py
adelecv/api/__init__.py
adelecv/api/config/__init__.py
adelecv/api/config/default.py
adelecv/api/data/__init__.py
adelecv/api/data/segmentations/__init__.py
adelecv/api/data/segmentations/dataset.py
adelecv/api/data/segmentations/torch_dataset.py
adelecv/api/data/segmentations/types.py
adelecv/api/logs/__init__.py
adelecv/api/logs/handlers.py
adelecv/api/logs/utils.py
adelecv/api/models/__init__.py
adelecv/api/models/base/__init__.py
adelecv/api/models/base/base_model.py
adelecv/api/models/segmentations/__init__.py
adelecv/api/models/segmentations/functional.py
adelecv/api/models/segmentations/segmentation_model.py
adelecv/api/models/segmentations/utils.py
adelecv/api/models/tensorboard_logger/__init__.py
adelecv/api/models/tensorboard_logger/tensorboard_logger.py
adelecv/api/modification_models/__init__.py
adelecv/api/modification_models/convert.py
adelecv/api/modification_models/conveter.py
adelecv/api/modification_models/export.py
adelecv/api/optimize/__init__.py
adelecv/api/optimize/segmentations/__init__.py
adelecv/api/optimize/segmentations/functional.py
adelecv/api/optimize/segmentations/hp_optimizer.py
adelecv/api/optimize/segmentations/hyper_params.py
adelecv/ui/__init__.py
adelecv/ui/dashboard/__init__.py
adelecv/ui/dashboard/app.py
adelecv/ui/dashboard/assets/script.js
adelecv/ui/dashboard/assets/style.css
adelecv/ui/dashboard/callbacks/__init__.py
adelecv/ui/dashboard/callbacks/console.py
adelecv/ui/dashboard/callbacks/dataset.py
adelecv/ui/dashboard/callbacks/notifications.py
adelecv/ui/dashboard/callbacks/table_models.py
adelecv/ui/dashboard/callbacks/train.py
adelecv/ui/dashboard/components/__init__.py
adelecv/ui/dashboard/components/console.py
adelecv/ui/dashboard/components/dataset.py
adelecv/ui/dashboard/components/homepage.py
adelecv/ui/dashboard/components/navbar.py
adelecv/ui/dashboard/components/table_models.py
adelecv/ui/dashboard/components/train.py
adelecv/ui/dashboard/index.py
adelecv/ui/dashboard/task/__init__.py
adelecv-0.0.2.dist-info/LICENSE
adelecv-0.0.2.dist-info/METADATA
adelecv-0.0.2.dist-info/WHEEL
adelecv-0.0.2.dist-info/entry_points.txt
adelecv-0.0.2.dist-info/RECORD
