Metadata-Version: 2.1
Name: adelecv
Version: 0.0.2
Summary: 
Author: Denis Mamatin
Author-email: mamatin-denis@yandex.ru
Requires-Python: >=3.9,<4.0
Classifier: License :: OSI Approved :: MIT License
Classifier: Operating System :: OS Independent
Classifier: Programming Language :: Python :: 3
Classifier: Programming Language :: Python :: 3.9
Classifier: Programming Language :: Python :: 3.10
Classifier: Programming Language :: Python :: 3.11
Classifier: Programming Language :: Python :: 3
Requires-Dist: albumentations (>=1.3.0,<2.0.0)
Requires-Dist: click (>=8.1.3,<9.0.0)
Requires-Dist: dash (>=2.8.1,<3.0.0)
Requires-Dist: dash-bootstrap-components (>=1.4.0,<2.0.0)
Requires-Dist: dash-extensions (>=0.1.13,<0.2.0)
Requires-Dist: dash-mantine-components (>=0.11.1,<0.12.0)
Requires-Dist: fiftyone (>=0.19.1,<0.20.0)
Requires-Dist: kaleido (==0.2.1)
Requires-Dist: opencv-python (>=4.7.0.72,<5.0.0.0)
Requires-Dist: optuna (>=3.1.0,<4.0.0)
Requires-Dist: pandas (>=1.5.3,<2.0.0)
Requires-Dist: pydantic (>=1.10.5,<2.0.0)
Requires-Dist: python-dotenv (>=1.0.0,<2.0.0)
Requires-Dist: segmentation-models-pytorch (>=0.3.2,<0.4.0)
Requires-Dist: tensorboard (>=2.12.0,<3.0.0)
Requires-Dist: tqdm (>=4.64.1,<5.0.0)
